ligo/followup_advocate/__init__.py
ligo/followup_advocate/jinja.py
ligo/followup_advocate/tool.py
ligo/followup_advocate/templates/RAVEN_circular.jinja2
ligo/followup_advocate/templates/RAVEN_subject.jinja2
ligo/followup_advocate/templates/__init__.py
ligo/followup_advocate/templates/authors.jinja2
ligo/followup_advocate/templates/cgmi.jinja2
ligo/followup_advocate/templates/combine_skymaps.jinja2
ligo/followup_advocate/templates/compare_skymaps.jinja2
ligo/followup_advocate/templates/em_bright.jinja2
ligo/followup_advocate/templates/initial_body.jinja2
ligo/followup_advocate/templates/initial_circular.jinja2
ligo/followup_advocate/templates/llama_alert_circular.jinja2
ligo/followup_advocate/templates/llama_subject.jinja2
ligo/followup_advocate/templates/llama_track_circular.jinja2
ligo/followup_advocate/templates/macros.jinja2
ligo/followup_advocate/templates/medium_latency_grb_circular.jinja2
ligo/followup_advocate/templates/medium_latency_grb_detection_circular.jinja2
ligo/followup_advocate/templates/medium_latency_grb_exclusion_circular.jinja2
ligo/followup_advocate/templates/medium_latency_grb_subject.jinja2
ligo/followup_advocate/templates/numbered_pipeline_citations.jinja2
ligo/followup_advocate/templates/p_astro.jinja2
ligo/followup_advocate/templates/retraction.jinja2
ligo/followup_advocate/templates/skymap_info.jinja2
ligo/followup_advocate/templates/subject.jinja2
ligo/followup_advocate/templates/update_circular.jinja2
ligo/followup_advocate/templates/userguide_conclusion.jinja2
ligo/followup_advocate/test/__init__.py
ligo/followup_advocate/test/test_circular_text.py
ligo/followup_advocate/test/test_tool.py
ligo/followup_advocate/test/data/E1122/event.json
ligo/followup_advocate/test/data/E1122/files.json
ligo/followup_advocate/test/data/E1122/files/distances_pygrb.json
ligo/followup_advocate/test/data/E1122/files/distances_x.json
ligo/followup_advocate/test/data/E1122/files/false_alarm_probability_pygrb.json
ligo_followup_advocate-1.3.10.dist-info/licenses/COPYING.md
ligo_followup_advocate-1.3.10.dist-info/METADATA
ligo_followup_advocate-1.3.10.dist-info/WHEEL
ligo_followup_advocate-1.3.10.dist-info/entry_points.txt
ligo_followup_advocate-1.3.10.dist-info/top_level.txt
ligo_followup_advocate-1.3.10.dist-info/RECORD
