Metadata-Version: 2.4
Name: ligo-followup-advocate
Version: 1.3.10
Summary: LIGO/Virgo/KAGRA Follow-up Advocate Tools
Author-email: Leo Singer <leo.singer@ligo.org>, Brandon Piotrzkowski <brandon.piotrzkowski@ligo.org>
License: GPL-2+
Project-URL: homepage, https://git.ligo.org/emfollow/ligo-followup-advocate
Classifier: Intended Audience :: Science/Research
Classifier: License :: OSI Approved :: GNU General Public License v2 or later (GPLv2+)
Classifier: Operating System :: POSIX
Classifier: Programming Language :: Python :: 3.11
Classifier: Programming Language :: Python :: 3.12
Classifier: Programming Language :: Python :: 3.13
Classifier: Topic :: Scientific/Engineering :: Astronomy
Classifier: Topic :: Scientific/Engineering :: Physics
Requires-Python: >=3.11
License-File: COPYING.md
Requires-Dist: astropy
Requires-Dist: humanize
Requires-Dist: jinja2
Requires-Dist: ligo-gracedb>=1.29.dev1
Requires-Dist: ligo.skymap>=1.1.1
Requires-Dist: lxml
Requires-Dist: numpy
Provides-Extra: test
Requires-Dist: pytest>=3.0; extra == "test"
Requires-Dist: pytest-mock; extra == "test"
Dynamic: license-file
